{
    "Ar36": {
        "error": 3.1981154200845194e-07,
        "error_type": "",
        "fit": "previous",
        "references": [
            {
                "exclude": false,
                "record_id": "ba-01-n-15593"
            }
        ],
        "value": 2.1143138938025524e-06
    },
    "Ar37": {
        "error": 3.0889120964879346e-07,
        "error_type": "",
        "fit": "previous",
        "references": [
            {
                "exclude": false,
                "record_id": "ba-01-n-15593"
            }
        ],
        "value": -3.769531374180494e-07
    },
    "Ar38": {
        "error": 2.189374304275328e-07,
        "error_type": "",
        "fit": "previous",
        "references": [
            {
                "exclude": false,
                "record_id": "ba-01-n-15593"
            }
        ],
        "value": -6.134337520435082e-07
    },
    "Ar39": {
        "error": 2.5499930602541026e-07,
        "error_type": "",
        "fit": "previous",
        "references": [
            {
                "exclude": false,
                "record_id": "ba-01-n-15593"
            }
        ],
        "value": -3.146657529045304e-07
    },
    "Ar40": {
        "error": 1.282599993578888e-06,
        "error_type": "",
        "fit": "previous",
        "references": [
            {
                "exclude": false,
                "record_id": "ba-01-n-15593"
            }
        ],
        "value": 1.346543213804682e-05
    }
}